sensitive_data_validator/__init__.py
sensitive_data_validator/sensitive_api.py
sensitive_data_validator/data_processor/__init__.py
sensitive_data_validator/data_processor/file_processor.py
sensitive_data_validator/utils/__init__.py
sensitive_data_validator/utils/gcs_handler.py
sensitive_data_validator/utils/result_handler.py
sensitive_data_validator/validators/__init__.py
sensitive_data_validator/validators/validators.py
sensitive_data_validator-0.2.3.dist-info/METADATA
sensitive_data_validator-0.2.3.dist-info/WHEEL
sensitive_data_validator-0.2.3.dist-info/entry_points.txt
sensitive_data_validator-0.2.3.dist-info/top_level.txt
sensitive_data_validator-0.2.3.dist-info/RECORD
