Metadata-Version: 2.1
Name: sensitive-data-validator
Version: 0.2.3
Summary: A package to validate sensitive data in various file formats.
Home-page: https://yourrepository.url
Author: Guilherme Duarte
Author-email: guilherme.henrique@exa.com.br
License: UNKNOWN
Platform: UNKNOWN
Classifier: Programming Language :: Python :: 3
Classifier: License :: OSI Approved :: MIT License
Classifier: Operating System :: OS Independent
Requires-Python: >=3.6
Requires-Dist: google-cloud-logging
Requires-Dist: google-cloud-storage
Requires-Dist: pandas
Requires-Dist: validate-docbr
